pyjipamlib/__init__.py
pyjipamlib/utils.py
pyjipamlib-0.0.22.dist-info/METADATA
pyjipamlib-0.0.22.dist-info/WHEEL
pyjipamlib-0.0.22.dist-info/licenses/LICENSE
pyjipamlib-0.0.22.dist-info/RECORD
