Metadata-Version: 2.1
Name: pyjipamlib
Version: 0.0.22
Summary: jipam libs
Project-URL: Homepage, https://github.com/jgajardog/pyjipamlib
Author-email: jgajardo <jgajardo@gmail.com>
License-File: LICENSE
Classifier: License :: OSI Approved :: MIT License
Classifier: Operating System :: OS Independent
Classifier: Programming Language :: Python :: 3
Requires-Python: >=3.6
